wash/__init__.py
wash/utils.py
dict_wash-0.69.1.dist-info/METADATA
dict_wash-0.69.1.dist-info/WHEEL
dict_wash-0.69.1.dist-info/top_level.txt
dict_wash-0.69.1.dist-info/RECORD
